bm23id24_xas/LCA.py
bm23id24_xas/MCR_ALS.py
bm23id24_xas/__init__.py
bm23id24_xas/pca_estimator.py
bm23id24_xas/xas_v2_6.py
bm23id24_xas/xasproc_v2_82.py
bm23id24_xas-0.0.13.dist-info/LICENSE.md
bm23id24_xas-0.0.13.dist-info/METADATA
bm23id24_xas-0.0.13.dist-info/WHEEL
bm23id24_xas-0.0.13.dist-info/top_level.txt
bm23id24_xas-0.0.13.dist-info/RECORD
