Metadata-Version: 2.2
Name: bm23id24_xas
Version: 0.0.13
Summary: Library for XAS data analysis
Author: Molokova, Lomachenko, Lopez Romero
License-File: LICENSE.md
Requires-Dist: xraylarch
Requires-Dist: pymcr
Requires-Dist: pyfitit
Requires-Dist: h5py
Dynamic: author
Dynamic: description
Dynamic: requires-dist
Dynamic: summary
